MANIFEST.in
setup.py
QtIPy/QtIPy.py
QtIPy/__init__.py
QtIPy/cmd.py
QtIPy/config.py
QtIPy/qt.py
QtIPy/translate.py
QtIPy/utils.py
QtIPy.egg-info/PKG-INFO
QtIPy.egg-info/SOURCES.txt
QtIPy.egg-info/dependency_links.txt
QtIPy.egg-info/entry_points.txt
QtIPy.egg-info/requires.txt
QtIPy.egg-info/top_level.txt
qtipy/QtIPy.py
qtipy/__init__.py
qtipy/cmd.py
qtipy/config.py
qtipy/qt.py
qtipy/translate.py
qtipy/utils.py
qtipy/icons/arrow-090.png
qtipy/icons/arrow-270.png
qtipy/icons/arrow-circle-315.png
qtipy/icons/clipboard-paste.png
qtipy/icons/clock-select-sm.png
qtipy/icons/clock-select.png
qtipy/icons/control-pause.png
qtipy/icons/control-stop-square.png
qtipy/icons/control.png
qtipy/icons/copy.png
qtipy/icons/cross.png
qtipy/icons/cut.png
qtipy/icons/disk-sm.png
qtipy/icons/disk.png
qtipy/icons/document-attribute-i-sm.png
qtipy/icons/document-attribute-i.png
qtipy/icons/document-copy-sm.png
qtipy/icons/document-copy.png
qtipy/icons/edit-diff.png
qtipy/icons/folder-horizontal-open-sm.png
qtipy/icons/folder-horizontal-open.png
qtipy/icons/hand-finger-sm.png
qtipy/icons/hand-finger.png
qtipy/icons/ipynotebook.png
qtipy/icons/play.png
qtipy/icons/plus-circle.png
qtipy/icons/property.png
qtipy/icons/qtipy-sm.png
qtipy/icons/scissors.png
qtipy/static/.DS_Store
qtipy/static/icon.icns
qtipy/static/icon.png